{
  "sneakers": [
    {
      "img": "/img/sneakers/sneakers1.png",
      "title": "Мужские Кроссовки Nike Blazer Mid Suede",
      "price": 12999,
      "id": 1
    },
    {
      "img": "/img/sneakers/sneakers2.png",
      "title": "Мужские Кроссовки Nike Air Max 270",
      "price": 8499,
      "id": 2
    },
    {
      "img": "/img/sneakers/sneakers3.png",
      "title": "Мужские Кроссовки Nike Blazer Mid Suede",
      "price": 8999,
      "id": 3
    },
    {
      "img": "/img/sneakers/sneakers4.png",
      "title": "Кроссовки Puma X Aka Boku Future Rider",
      "price": 12999,
      "id": 4
    },
    {
      "img": "/img/sneakers/sneakers5.png",
      "title": "Мужские Кроссовки Under Armour Curry 8",
      "price": 15199,
      "id": 5
    },
    {
      "img": "/img/sneakers/image5.png",
      "title": "Мужские Кроссовки Nike Kyrie 7",
      "price": 11299,
      "id": 6
    },
    {
      "img": "/img/sneakers/image5-2.png",
      "title": "Мужские Кроссовки Jordan Air Jordan 11",
      "price": 10799,
      "id": 7
    },
    {
      "img": "/img/sneakers/image5-3.png",
      "title": "Мужские Кроссовки Nike LeBron XVIII",
      "price": 16499,
      "id": 8
    },
    {
      "img": "/img/sneakers/image5-4.png",
      "title": "Мужские Кроссовки Nike Lebron XVIII Low",
      "price": 13499,
      "id": 9
    },
    {
      "img": "/img/sneakers/image5-5.png",
      "title": "Мужские Кроссовки Nike Blazer Mid Suede",
      "price": 8499,
      "id": 10
    },
    {
      "img": "/img/sneakers/image5-6.png",
      "title": "Кроссовки Puma X Aka Boku Future Rider",
      "price": 8999,
      "id": 11
    },
    {
      "img": "/img/sneakers/image5-1.png",
      "title": "Мужские Кроссовки Nike Kyrie Flytrap IV",
      "price": 11299,
      "id": 12
    }
  ],
  "card": [],
  "liked": []
}